<?xml version="1.0" encoding="utf-8" ?>
<KidsObjDB version="0" platform="16" name_file="0x008d9ce5">
    <Object version="0" name="0x064ad76c" type="TypeInfo::Object::Render::Texture::StaticForSLE">
        <Column name="Width" type="int32">
            <Row value="128" />
        </Column>
        <Column name="Height" type="int32">
            <Row value="8" />
        </Column>
        <Column name="MipLodBias" type="float">
            <Row value="0.0" />
        </Column>
        <Column name="LevelNum" type="uint8">
            <Row value="0x01" />
        </Column>
        <Column name="MinMipLevel" type="uint8">
            <Row value="0x00" />
        </Column>
        <Column name="PixelFormat" type="uint8">
            <Row value="0x01" />
        </Column>
        <Column name="ColorSpace" type="uint8">
            <Row value="0x01" />
        </Column>
        <Column name="Usage" type="uint8">
            <Row value="0x00" />
        </Column>
        <Column name="AddressU" type="uint8">
            <Row value="0x01" />
        </Column>
        <Column name="AddressV" type="uint8">
            <Row value="0x01" />
        </Column>
        <Column name="MagFilter" type="uint8">
            <Row value="0x01" />
        </Column>
        <Column name="MinFilter" type="uint8">
            <Row value="0x01" />
        </Column>
        <Column name="MipFilter" type="uint8">
            <Row value="0x02" />
        </Column>
        <Column name="AnisoSampleNum" type="uint8">
            <Row value="0x00" />
        </Column>
        <Column name="LocationHint" type="uint8">
            <Row value="0x00" />
        </Column>
        <Column name="InitColorResourceObjNameHash" type="uint32">
            <Row value="0x5f1da260" />
        </Column>
    </Object>
    <Object version="0" name="0x0673bd5a" type="TypeInfo::Object::Render::Texture::StaticForSLE">
        <Column name="Width" type="int32">
            <Row value="40" />
        </Column>
        <Column name="Height" type="int32">
            <Row value="40" />
        </Column>
        <Column name="MipLodBias" type="float">
            <Row value="0.0" />
        </Column>
        <Column name="LevelNum" type="uint8">
            <Row value="0x01" />
        </Column>
        <Column name="MinMipLevel" type="uint8">
            <Row value="0x00" />
        </Column>
        <Column name="PixelFormat" type="uint8">
            <Row value="0x01" />
        </Column>
        <Column name="ColorSpace" type="uint8">
            <Row value="0x01" />
        </Column>
        <Column name="Usage" type="uint8">
            <Row value="0x00" />
        </Column>
        <Column name="AddressU" type="uint8">
            <Row value="0x01" />
        </Column>
        <Column name="AddressV" type="uint8">
            <Row value="0x01" />
        </Column>
        <Column name="MagFilter" type="uint8">
            <Row value="0x01" />
        </Column>
        <Column name="MinFilter" type="uint8">
            <Row value="0x01" />
        </Column>
        <Column name="MipFilter" type="uint8">
            <Row value="0x02" />
        </Column>
        <Column name="AnisoSampleNum" type="uint8">
            <Row value="0x00" />
        </Column>
        <Column name="LocationHint" type="uint8">
            <Row value="0x00" />
        </Column>
        <Column name="InitColorResourceObjNameHash" type="uint32">
            <Row value="0x64117a32" />
        </Column>
    </Object>
    <Object version="0" name="0x1a6d21bb" type="TypeInfo::Object::Render::Texture::StaticForSLE">
        <Column name="Width" type="int32">
            <Row value="148" />
        </Column>
        <Column name="Height" type="int32">
            <Row value="28" />
        </Column>
        <Column name="MipLodBias" type="float">
            <Row value="0.0" />
        </Column>
        <Column name="LevelNum" type="uint8">
            <Row value="0x01" />
        </Column>
        <Column name="MinMipLevel" type="uint8">
            <Row value="0x00" />
        </Column>
        <Column name="PixelFormat" type="uint8">
            <Row value="0x01" />
        </Column>
        <Column name="ColorSpace" type="uint8">
            <Row value="0x01" />
        </Column>
        <Column name="Usage" type="uint8">
            <Row value="0x00" />
        </Column>
        <Column name="AddressU" type="uint8">
            <Row value="0x01" />
        </Column>
        <Column name="AddressV" type="uint8">
            <Row value="0x01" />
        </Column>
        <Column name="MagFilter" type="uint8">
            <Row value="0x01" />
        </Column>
        <Column name="MinFilter" type="uint8">
            <Row value="0x01" />
        </Column>
        <Column name="MipFilter" type="uint8">
            <Row value="0x02" />
        </Column>
        <Column name="AnisoSampleNum" type="uint8">
            <Row value="0x00" />
        </Column>
        <Column name="LocationHint" type="uint8">
            <Row value="0x00" />
        </Column>
        <Column name="InitColorResourceObjNameHash" type="uint32">
            <Row value="0xcf44a1f1" />
        </Column>
    </Object>
    <Object version="0" name="0x1ac4ca3a" type="TypeInfo::Object::Render::Texture::StaticForSLE">
        <Column name="Width" type="int32">
            <Row value="4" />
        </Column>
        <Column name="Height" type="int32">
            <Row value="4" />
        </Column>
        <Column name="MipLodBias" type="float">
            <Row value="0.0" />
        </Column>
        <Column name="LevelNum" type="uint8">
            <Row value="0x01" />
        </Column>
        <Column name="MinMipLevel" type="uint8">
            <Row value="0x00" />
        </Column>
        <Column name="PixelFormat" type="uint8">
            <Row value="0x01" />
        </Column>
        <Column name="ColorSpace" type="uint8">
            <Row value="0x01" />
        </Column>
        <Column name="Usage" type="uint8">
            <Row value="0x00" />
        </Column>
        <Column name="AddressU" type="uint8">
            <Row value="0x01" />
        </Column>
        <Column name="AddressV" type="uint8">
            <Row value="0x01" />
        </Column>
        <Column name="MagFilter" type="uint8">
            <Row value="0x01" />
        </Column>
        <Column name="MinFilter" type="uint8">
            <Row value="0x01" />
        </Column>
        <Column name="MipFilter" type="uint8">
            <Row value="0x02" />
        </Column>
        <Column name="AnisoSampleNum" type="uint8">
            <Row value="0x00" />
        </Column>
        <Column name="LocationHint" type="uint8">
            <Row value="0x00" />
        </Column>
        <Column name="InitColorResourceObjNameHash" type="uint32">
            <Row value="0xd9e20952" />
        </Column>
    </Object>
    <Object version="0" name="0x2e51e561" type="TypeInfo::Object::Render::Texture::StaticForSLE">
        <Column name="Width" type="int32">
            <Row value="128" />
        </Column>
        <Column name="Height" type="int32">
            <Row value="8" />
        </Column>
        <Column name="MipLodBias" type="float">
            <Row value="0.0" />
        </Column>
        <Column name="LevelNum" type="uint8">
            <Row value="0x01" />
        </Column>
        <Column name="MinMipLevel" type="uint8">
            <Row value="0x00" />
        </Column>
        <Column name="PixelFormat" type="uint8">
            <Row value="0x01" />
        </Column>
        <Column name="ColorSpace" type="uint8">
            <Row value="0x01" />
        </Column>
        <Column name="Usage" type="uint8">
            <Row value="0x00" />
        </Column>
        <Column name="AddressU" type="uint8">
            <Row value="0x01" />
        </Column>
        <Column name="AddressV" type="uint8">
            <Row value="0x01" />
        </Column>
        <Column name="MagFilter" type="uint8">
            <Row value="0x01" />
        </Column>
        <Column name="MinFilter" type="uint8">
            <Row value="0x01" />
        </Column>
        <Column name="MipFilter" type="uint8">
            <Row value="0x02" />
        </Column>
        <Column name="AnisoSampleNum" type="uint8">
            <Row value="0x00" />
        </Column>
        <Column name="LocationHint" type="uint8">
            <Row value="0x00" />
        </Column>
        <Column name="InitColorResourceObjNameHash" type="uint32">
            <Row value="0x37f8530b" />
        </Column>
    </Object>
    <Object version="0" name="0x328d23f0" type="TypeInfo::Object::Render::Texture::StaticForSLE">
        <Column name="Width" type="int32">
            <Row value="148" />
        </Column>
        <Column name="Height" type="int32">
            <Row value="28" />
        </Column>
        <Column name="MipLodBias" type="float">
            <Row value="0.0" />
        </Column>
        <Column name="LevelNum" type="uint8">
            <Row value="0x01" />
        </Column>
        <Column name="MinMipLevel" type="uint8">
            <Row value="0x00" />
        </Column>
        <Column name="PixelFormat" type="uint8">
            <Row value="0x01" />
        </Column>
        <Column name="ColorSpace" type="uint8">
            <Row value="0x01" />
        </Column>
        <Column name="Usage" type="uint8">
            <Row value="0x00" />
        </Column>
        <Column name="AddressU" type="uint8">
            <Row value="0x01" />
        </Column>
        <Column name="AddressV" type="uint8">
            <Row value="0x01" />
        </Column>
        <Column name="MagFilter" type="uint8">
            <Row value="0x01" />
        </Column>
        <Column name="MinFilter" type="uint8">
            <Row value="0x01" />
        </Column>
        <Column name="MipFilter" type="uint8">
            <Row value="0x02" />
        </Column>
        <Column name="AnisoSampleNum" type="uint8">
            <Row value="0x00" />
        </Column>
        <Column name="LocationHint" type="uint8">
            <Row value="0x00" />
        </Column>
        <Column name="InitColorResourceObjNameHash" type="uint32">
            <Row value="0xbb24e65c" />
        </Column>
    </Object>
    <Object version="0" name="0x3f993195" type="TypeInfo::Object::Render::Texture::StaticForSLE">
        <Column name="Width" type="int32">
            <Row value="64" />
        </Column>
        <Column name="Height" type="int32">
            <Row value="64" />
        </Column>
        <Column name="MipLodBias" type="float">
            <Row value="0.0" />
        </Column>
        <Column name="LevelNum" type="uint8">
            <Row value="0x01" />
        </Column>
        <Column name="MinMipLevel" type="uint8">
            <Row value="0x00" />
        </Column>
        <Column name="PixelFormat" type="uint8">
            <Row value="0x01" />
        </Column>
        <Column name="ColorSpace" type="uint8">
            <Row value="0x01" />
        </Column>
        <Column name="Usage" type="uint8">
            <Row value="0x00" />
        </Column>
        <Column name="AddressU" type="uint8">
            <Row value="0x01" />
        </Column>
        <Column name="AddressV" type="uint8">
            <Row value="0x01" />
        </Column>
        <Column name="MagFilter" type="uint8">
            <Row value="0x01" />
        </Column>
        <Column name="MinFilter" type="uint8">
            <Row value="0x01" />
        </Column>
        <Column name="MipFilter" type="uint8">
            <Row value="0x02" />
        </Column>
        <Column name="AnisoSampleNum" type="uint8">
            <Row value="0x00" />
        </Column>
        <Column name="LocationHint" type="uint8">
            <Row value="0x00" />
        </Column>
        <Column name="InitColorResourceObjNameHash" type="uint32">
            <Row value="0x4f9a8d57" />
        </Column>
    </Object>
    <Object version="0" name="0x5937672b" type="TypeInfo::Object::Render::Texture::StaticForSLE">
        <Column name="Width" type="int32">
            <Row value="20" />
        </Column>
        <Column name="Height" type="int32">
            <Row value="40" />
        </Column>
        <Column name="MipLodBias" type="float">
            <Row value="0.0" />
        </Column>
        <Column name="LevelNum" type="uint8">
            <Row value="0x01" />
        </Column>
        <Column name="MinMipLevel" type="uint8">
            <Row value="0x00" />
        </Column>
        <Column name="PixelFormat" type="uint8">
            <Row value="0x01" />
        </Column>
        <Column name="ColorSpace" type="uint8">
            <Row value="0x01" />
        </Column>
        <Column name="Usage" type="uint8">
            <Row value="0x00" />
        </Column>
        <Column name="AddressU" type="uint8">
            <Row value="0x01" />
        </Column>
        <Column name="AddressV" type="uint8">
            <Row value="0x01" />
        </Column>
        <Column name="MagFilter" type="uint8">
            <Row value="0x01" />
        </Column>
        <Column name="MinFilter" type="uint8">
            <Row value="0x01" />
        </Column>
        <Column name="MipFilter" type="uint8">
            <Row value="0x02" />
        </Column>
        <Column name="AnisoSampleNum" type="uint8">
            <Row value="0x00" />
        </Column>
        <Column name="LocationHint" type="uint8">
            <Row value="0x00" />
        </Column>
        <Column name="InitColorResourceObjNameHash" type="uint32">
            <Row value="0x69c30a81" />
        </Column>
    </Object>
    <Object version="0" name="0x8f86d0db" type="TypeInfo::Object::Render::Texture::StaticForSLE">
        <Column name="Width" type="int32">
            <Row value="64" />
        </Column>
        <Column name="Height" type="int32">
            <Row value="64" />
        </Column>
        <Column name="MipLodBias" type="float">
            <Row value="0.0" />
        </Column>
        <Column name="LevelNum" type="uint8">
            <Row value="0x01" />
        </Column>
        <Column name="MinMipLevel" type="uint8">
            <Row value="0x00" />
        </Column>
        <Column name="PixelFormat" type="uint8">
            <Row value="0x01" />
        </Column>
        <Column name="ColorSpace" type="uint8">
            <Row value="0x01" />
        </Column>
        <Column name="Usage" type="uint8">
            <Row value="0x00" />
        </Column>
        <Column name="AddressU" type="uint8">
            <Row value="0x01" />
        </Column>
        <Column name="AddressV" type="uint8">
            <Row value="0x01" />
        </Column>
        <Column name="MagFilter" type="uint8">
            <Row value="0x01" />
        </Column>
        <Column name="MinFilter" type="uint8">
            <Row value="0x01" />
        </Column>
        <Column name="MipFilter" type="uint8">
            <Row value="0x02" />
        </Column>
        <Column name="AnisoSampleNum" type="uint8">
            <Row value="0x00" />
        </Column>
        <Column name="LocationHint" type="uint8">
            <Row value="0x00" />
        </Column>
        <Column name="InitColorResourceObjNameHash" type="uint32">
            <Row value="0xfd60d6d1" />
        </Column>
    </Object>
    <Object version="0" name="0x8fc95c15" type="TypeInfo::Object::Render::Texture::StaticForSLE">
        <Column name="Width" type="int32">
            <Row value="32" />
        </Column>
        <Column name="Height" type="int32">
            <Row value="32" />
        </Column>
        <Column name="MipLodBias" type="float">
            <Row value="0.0" />
        </Column>
        <Column name="LevelNum" type="uint8">
            <Row value="0x01" />
        </Column>
        <Column name="MinMipLevel" type="uint8">
            <Row value="0x00" />
        </Column>
        <Column name="PixelFormat" type="uint8">
            <Row value="0x01" />
        </Column>
        <Column name="ColorSpace" type="uint8">
            <Row value="0x01" />
        </Column>
        <Column name="Usage" type="uint8">
            <Row value="0x00" />
        </Column>
        <Column name="AddressU" type="uint8">
            <Row value="0x01" />
        </Column>
        <Column name="AddressV" type="uint8">
            <Row value="0x01" />
        </Column>
        <Column name="MagFilter" type="uint8">
            <Row value="0x01" />
        </Column>
        <Column name="MinFilter" type="uint8">
            <Row value="0x01" />
        </Column>
        <Column name="MipFilter" type="uint8">
            <Row value="0x02" />
        </Column>
        <Column name="AnisoSampleNum" type="uint8">
            <Row value="0x00" />
        </Column>
        <Column name="LocationHint" type="uint8">
            <Row value="0x00" />
        </Column>
        <Column name="InitColorResourceObjNameHash" type="uint32">
            <Row value="0x056fb2d7" />
        </Column>
    </Object>
    <Object version="0" name="0xa06a67fa" type="TypeInfo::Object::Render::Texture::StaticForSLE">
        <Column name="Width" type="int32">
            <Row value="16" />
        </Column>
        <Column name="Height" type="int32">
            <Row value="16" />
        </Column>
        <Column name="MipLodBias" type="float">
            <Row value="0.0" />
        </Column>
        <Column name="LevelNum" type="uint8">
            <Row value="0x01" />
        </Column>
        <Column name="MinMipLevel" type="uint8">
            <Row value="0x00" />
        </Column>
        <Column name="PixelFormat" type="uint8">
            <Row value="0x01" />
        </Column>
        <Column name="ColorSpace" type="uint8">
            <Row value="0x01" />
        </Column>
        <Column name="Usage" type="uint8">
            <Row value="0x00" />
        </Column>
        <Column name="AddressU" type="uint8">
            <Row value="0x01" />
        </Column>
        <Column name="AddressV" type="uint8">
            <Row value="0x01" />
        </Column>
        <Column name="MagFilter" type="uint8">
            <Row value="0x01" />
        </Column>
        <Column name="MinFilter" type="uint8">
            <Row value="0x01" />
        </Column>
        <Column name="MipFilter" type="uint8">
            <Row value="0x02" />
        </Column>
        <Column name="AnisoSampleNum" type="uint8">
            <Row value="0x00" />
        </Column>
        <Column name="LocationHint" type="uint8">
            <Row value="0x00" />
        </Column>
        <Column name="InitColorResourceObjNameHash" type="uint32">
            <Row value="0x08f02392" />
        </Column>
    </Object>
    <Object version="0" name="0xb3745bad" type="TypeInfo::Object::Render::Texture::StaticForSLE">
        <Column name="Width" type="int32">
            <Row value="32" />
        </Column>
        <Column name="Height" type="int32">
            <Row value="32" />
        </Column>
        <Column name="MipLodBias" type="float">
            <Row value="0.0" />
        </Column>
        <Column name="LevelNum" type="uint8">
            <Row value="0x01" />
        </Column>
        <Column name="MinMipLevel" type="uint8">
            <Row value="0x00" />
        </Column>
        <Column name="PixelFormat" type="uint8">
            <Row value="0x01" />
        </Column>
        <Column name="ColorSpace" type="uint8">
            <Row value="0x01" />
        </Column>
        <Column name="Usage" type="uint8">
            <Row value="0x00" />
        </Column>
        <Column name="AddressU" type="uint8">
            <Row value="0x01" />
        </Column>
        <Column name="AddressV" type="uint8">
            <Row value="0x01" />
        </Column>
        <Column name="MagFilter" type="uint8">
            <Row value="0x01" />
        </Column>
        <Column name="MinFilter" type="uint8">
            <Row value="0x01" />
        </Column>
        <Column name="MipFilter" type="uint8">
            <Row value="0x02" />
        </Column>
        <Column name="AnisoSampleNum" type="uint8">
            <Row value="0x00" />
        </Column>
        <Column name="LocationHint" type="uint8">
            <Row value="0x00" />
        </Column>
        <Column name="InitColorResourceObjNameHash" type="uint32">
            <Row value="0x5724a63f" />
        </Column>
    </Object>
    <Object version="0" name="0xbc05be81" type="TypeInfo::Object::Render::Texture::StaticForSLE">
        <Column name="Width" type="int32">
            <Row value="20" />
        </Column>
        <Column name="Height" type="int32">
            <Row value="40" />
        </Column>
        <Column name="MipLodBias" type="float">
            <Row value="0.0" />
        </Column>
        <Column name="LevelNum" type="uint8">
            <Row value="0x01" />
        </Column>
        <Column name="MinMipLevel" type="uint8">
            <Row value="0x00" />
        </Column>
        <Column name="PixelFormat" type="uint8">
            <Row value="0x01" />
        </Column>
        <Column name="ColorSpace" type="uint8">
            <Row value="0x01" />
        </Column>
        <Column name="Usage" type="uint8">
            <Row value="0x00" />
        </Column>
        <Column name="AddressU" type="uint8">
            <Row value="0x01" />
        </Column>
        <Column name="AddressV" type="uint8">
            <Row value="0x01" />
        </Column>
        <Column name="MagFilter" type="uint8">
            <Row value="0x01" />
        </Column>
        <Column name="MinFilter" type="uint8">
            <Row value="0x01" />
        </Column>
        <Column name="MipFilter" type="uint8">
            <Row value="0x02" />
        </Column>
        <Column name="AnisoSampleNum" type="uint8">
            <Row value="0x00" />
        </Column>
        <Column name="LocationHint" type="uint8">
            <Row value="0x00" />
        </Column>
        <Column name="InitColorResourceObjNameHash" type="uint32">
            <Row value="0x60bf9deb" />
        </Column>
    </Object>
    <Object version="0" name="0xc6386004" type="TypeInfo::Object::Render::Texture::StaticForSLE">
        <Column name="Width" type="int32">
            <Row value="4" />
        </Column>
        <Column name="Height" type="int32">
            <Row value="4" />
        </Column>
        <Column name="MipLodBias" type="float">
            <Row value="0.0" />
        </Column>
        <Column name="LevelNum" type="uint8">
            <Row value="0x01" />
        </Column>
        <Column name="MinMipLevel" type="uint8">
            <Row value="0x00" />
        </Column>
        <Column name="PixelFormat" type="uint8">
            <Row value="0x01" />
        </Column>
        <Column name="ColorSpace" type="uint8">
            <Row value="0x01" />
        </Column>
        <Column name="Usage" type="uint8">
            <Row value="0x00" />
        </Column>
        <Column name="AddressU" type="uint8">
            <Row value="0x01" />
        </Column>
        <Column name="AddressV" type="uint8">
            <Row value="0x01" />
        </Column>
        <Column name="MagFilter" type="uint8">
            <Row value="0x01" />
        </Column>
        <Column name="MinFilter" type="uint8">
            <Row value="0x01" />
        </Column>
        <Column name="MipFilter" type="uint8">
            <Row value="0x02" />
        </Column>
        <Column name="AnisoSampleNum" type="uint8">
            <Row value="0x00" />
        </Column>
        <Column name="LocationHint" type="uint8">
            <Row value="0x00" />
        </Column>
        <Column name="InitColorResourceObjNameHash" type="uint32">
            <Row value="0x9ce12cc8" />
        </Column>
    </Object>
    <Object version="0" name="0xd48eb9e5" type="TypeInfo::Object::Render::Texture::StaticForSLE">
        <Column name="Width" type="int32">
            <Row value="4" />
        </Column>
        <Column name="Height" type="int32">
            <Row value="4" />
        </Column>
        <Column name="MipLodBias" type="float">
            <Row value="0.0" />
        </Column>
        <Column name="LevelNum" type="uint8">
            <Row value="0x01" />
        </Column>
        <Column name="MinMipLevel" type="uint8">
            <Row value="0x00" />
        </Column>
        <Column name="PixelFormat" type="uint8">
            <Row value="0x01" />
        </Column>
        <Column name="ColorSpace" type="uint8">
            <Row value="0x01" />
        </Column>
        <Column name="Usage" type="uint8">
            <Row value="0x00" />
        </Column>
        <Column name="AddressU" type="uint8">
            <Row value="0x01" />
        </Column>
        <Column name="AddressV" type="uint8">
            <Row value="0x01" />
        </Column>
        <Column name="MagFilter" type="uint8">
            <Row value="0x01" />
        </Column>
        <Column name="MinFilter" type="uint8">
            <Row value="0x01" />
        </Column>
        <Column name="MipFilter" type="uint8">
            <Row value="0x02" />
        </Column>
        <Column name="AnisoSampleNum" type="uint8">
            <Row value="0x00" />
        </Column>
        <Column name="LocationHint" type="uint8">
            <Row value="0x00" />
        </Column>
        <Column name="InitColorResourceObjNameHash" type="uint32">
            <Row value="0x59560f07" />
        </Column>
    </Object>
    <Object version="0" name="0xe2068f2e" type="TypeInfo::Object::Render::Texture::StaticForSLE">
        <Column name="Width" type="int32">
            <Row value="64" />
        </Column>
        <Column name="Height" type="int32">
            <Row value="64" />
        </Column>
        <Column name="MipLodBias" type="float">
            <Row value="0.0" />
        </Column>
        <Column name="LevelNum" type="uint8">
            <Row value="0x01" />
        </Column>
        <Column name="MinMipLevel" type="uint8">
            <Row value="0x00" />
        </Column>
        <Column name="PixelFormat" type="uint8">
            <Row value="0x01" />
        </Column>
        <Column name="ColorSpace" type="uint8">
            <Row value="0x01" />
        </Column>
        <Column name="Usage" type="uint8">
            <Row value="0x00" />
        </Column>
        <Column name="AddressU" type="uint8">
            <Row value="0x01" />
        </Column>
        <Column name="AddressV" type="uint8">
            <Row value="0x01" />
        </Column>
        <Column name="MagFilter" type="uint8">
            <Row value="0x01" />
        </Column>
        <Column name="MinFilter" type="uint8">
            <Row value="0x01" />
        </Column>
        <Column name="MipFilter" type="uint8">
            <Row value="0x02" />
        </Column>
        <Column name="AnisoSampleNum" type="uint8">
            <Row value="0x00" />
        </Column>
        <Column name="LocationHint" type="uint8">
            <Row value="0x00" />
        </Column>
        <Column name="InitColorResourceObjNameHash" type="uint32">
            <Row value="0xfad8e2de" />
        </Column>
    </Object>
    <Object version="0" name="0xe2967588" type="TypeInfo::Object::Render::Texture::StaticForSLE">
        <Column name="Width" type="int32">
            <Row value="64" />
        </Column>
        <Column name="Height" type="int32">
            <Row value="64" />
        </Column>
        <Column name="MipLodBias" type="float">
            <Row value="0.0" />
        </Column>
        <Column name="LevelNum" type="uint8">
            <Row value="0x01" />
        </Column>
        <Column name="MinMipLevel" type="uint8">
            <Row value="0x00" />
        </Column>
        <Column name="PixelFormat" type="uint8">
            <Row value="0x01" />
        </Column>
        <Column name="ColorSpace" type="uint8">
            <Row value="0x01" />
        </Column>
        <Column name="Usage" type="uint8">
            <Row value="0x00" />
        </Column>
        <Column name="AddressU" type="uint8">
            <Row value="0x01" />
        </Column>
        <Column name="AddressV" type="uint8">
            <Row value="0x01" />
        </Column>
        <Column name="MagFilter" type="uint8">
            <Row value="0x01" />
        </Column>
        <Column name="MinFilter" type="uint8">
            <Row value="0x01" />
        </Column>
        <Column name="MipFilter" type="uint8">
            <Row value="0x02" />
        </Column>
        <Column name="AnisoSampleNum" type="uint8">
            <Row value="0x00" />
        </Column>
        <Column name="LocationHint" type="uint8">
            <Row value="0x00" />
        </Column>
        <Column name="InitColorResourceObjNameHash" type="uint32">
            <Row value="0x0c45c7c4" />
        </Column>
    </Object>
    <Object version="0" name="0xed3efd8c" type="TypeInfo::Object::Render::Texture::StaticForSLE">
        <Column name="Width" type="int32">
            <Row value="32" />
        </Column>
        <Column name="Height" type="int32">
            <Row value="4" />
        </Column>
        <Column name="MipLodBias" type="float">
            <Row value="0.0" />
        </Column>
        <Column name="LevelNum" type="uint8">
            <Row value="0x01" />
        </Column>
        <Column name="MinMipLevel" type="uint8">
            <Row value="0x00" />
        </Column>
        <Column name="PixelFormat" type="uint8">
            <Row value="0x01" />
        </Column>
        <Column name="ColorSpace" type="uint8">
            <Row value="0x01" />
        </Column>
        <Column name="Usage" type="uint8">
            <Row value="0x00" />
        </Column>
        <Column name="AddressU" type="uint8">
            <Row value="0x01" />
        </Column>
        <Column name="AddressV" type="uint8">
            <Row value="0x01" />
        </Column>
        <Column name="MagFilter" type="uint8">
            <Row value="0x01" />
        </Column>
        <Column name="MinFilter" type="uint8">
            <Row value="0x01" />
        </Column>
        <Column name="MipFilter" type="uint8">
            <Row value="0x02" />
        </Column>
        <Column name="AnisoSampleNum" type="uint8">
            <Row value="0x00" />
        </Column>
        <Column name="LocationHint" type="uint8">
            <Row value="0x00" />
        </Column>
        <Column name="InitColorResourceObjNameHash" type="uint32">
            <Row value="0x56ae4040" />
        </Column>
    </Object>
    <Object version="0" name="0xf0420367" type="TypeInfo::Object::Render::Texture::StaticForSLE">
        <Column name="Width" type="int32">
            <Row value="4" />
        </Column>
        <Column name="Height" type="int32">
            <Row value="4" />
        </Column>
        <Column name="MipLodBias" type="float">
            <Row value="0.0" />
        </Column>
        <Column name="LevelNum" type="uint8">
            <Row value="0x01" />
        </Column>
        <Column name="MinMipLevel" type="uint8">
            <Row value="0x00" />
        </Column>
        <Column name="PixelFormat" type="uint8">
            <Row value="0x01" />
        </Column>
        <Column name="ColorSpace" type="uint8">
            <Row value="0x01" />
        </Column>
        <Column name="Usage" type="uint8">
            <Row value="0x00" />
        </Column>
        <Column name="AddressU" type="uint8">
            <Row value="0x01" />
        </Column>
        <Column name="AddressV" type="uint8">
            <Row value="0x01" />
        </Column>
        <Column name="MagFilter" type="uint8">
            <Row value="0x01" />
        </Column>
        <Column name="MinFilter" type="uint8">
            <Row value="0x01" />
        </Column>
        <Column name="MipFilter" type="uint8">
            <Row value="0x02" />
        </Column>
        <Column name="AnisoSampleNum" type="uint8">
            <Row value="0x00" />
        </Column>
        <Column name="LocationHint" type="uint8">
            <Row value="0x00" />
        </Column>
        <Column name="InitColorResourceObjNameHash" type="uint32">
            <Row value="0xb40bf5c5" />
        </Column>
    </Object>
    <Object version="0" name="0xf0b86966" type="TypeInfo::Object::Render::Texture::StaticForSLE">
        <Column name="Width" type="int32">
            <Row value="8" />
        </Column>
        <Column name="Height" type="int32">
            <Row value="4" />
        </Column>
        <Column name="MipLodBias" type="float">
            <Row value="0.0" />
        </Column>
        <Column name="LevelNum" type="uint8">
            <Row value="0x01" />
        </Column>
        <Column name="MinMipLevel" type="uint8">
            <Row value="0x00" />
        </Column>
        <Column name="PixelFormat" type="uint8">
            <Row value="0x01" />
        </Column>
        <Column name="ColorSpace" type="uint8">
            <Row value="0x01" />
        </Column>
        <Column name="Usage" type="uint8">
            <Row value="0x00" />
        </Column>
        <Column name="AddressU" type="uint8">
            <Row value="0x01" />
        </Column>
        <Column name="AddressV" type="uint8">
            <Row value="0x01" />
        </Column>
        <Column name="MagFilter" type="uint8">
            <Row value="0x01" />
        </Column>
        <Column name="MinFilter" type="uint8">
            <Row value="0x01" />
        </Column>
        <Column name="MipFilter" type="uint8">
            <Row value="0x02" />
        </Column>
        <Column name="AnisoSampleNum" type="uint8">
            <Row value="0x00" />
        </Column>
        <Column name="LocationHint" type="uint8">
            <Row value="0x00" />
        </Column>
        <Column name="InitColorResourceObjNameHash" type="uint32">
            <Row value="0xc2624fa6" />
        </Column>
    </Object>
    <Object version="0" name="0xf12ecf65" type="TypeInfo::Object::Render::Texture::StaticForSLE">
        <Column name="Width" type="int32">
            <Row value="8" />
        </Column>
        <Column name="Height" type="int32">
            <Row value="8" />
        </Column>
        <Column name="MipLodBias" type="float">
            <Row value="0.0" />
        </Column>
        <Column name="LevelNum" type="uint8">
            <Row value="0x01" />
        </Column>
        <Column name="MinMipLevel" type="uint8">
            <Row value="0x00" />
        </Column>
        <Column name="PixelFormat" type="uint8">
            <Row value="0x01" />
        </Column>
        <Column name="ColorSpace" type="uint8">
            <Row value="0x01" />
        </Column>
        <Column name="Usage" type="uint8">
            <Row value="0x00" />
        </Column>
        <Column name="AddressU" type="uint8">
            <Row value="0x01" />
        </Column>
        <Column name="AddressV" type="uint8">
            <Row value="0x01" />
        </Column>
        <Column name="MagFilter" type="uint8">
            <Row value="0x01" />
        </Column>
        <Column name="MinFilter" type="uint8">
            <Row value="0x01" />
        </Column>
        <Column name="MipFilter" type="uint8">
            <Row value="0x02" />
        </Column>
        <Column name="AnisoSampleNum" type="uint8">
            <Row value="0x00" />
        </Column>
        <Column name="LocationHint" type="uint8">
            <Row value="0x00" />
        </Column>
        <Column name="InitColorResourceObjNameHash" type="uint32">
            <Row value="0xd0b8a987" />
        </Column>
    </Object>
    <Object version="0" name="0xf8790887" type="TypeInfo::Object::Render::State::3D::Textures">
        <Column name="TextureBindTableCSVFileResourceHash" type="uint32">
            <Row value="0x63fa4b25" />
        </Column>
        <Column name="TextureObjectNameHash" type="uint32">
            <Row value="0x00000000" />
        </Column>
    </Object>
</KidsObjDB>
