<?xml version="1.0" encoding="utf-8" ?>
<KidsObjDB version="0" platform="16" name_file="0x268ad461">
    <Object version="0" name="0x01cb0f78" type="TypeInfo::Object::MotorEventSetting">
        <Column name="ObjectDatabaseNameHashArray" type="uint32">
            <Row value="0xfea1e2e1" />
            <Row value="0x4599522e" />
            <Row value="0x56a7f78f" />
            <Row value="0x3839d642" />
            <Row value="0xbfd3e4b4" />
            <Row value="0x6fd8196d" />
            <Row value="0x288fa26d" />
            <Row value="0xa7be45aa" />
            <Row value="0x8f1c2d4e" />
        </Column>
        <Column name="DefaultStageKeyHashArray" type="uint32">
            <Row value="0x1f56cb18" />
        </Column>
        <Column name="DefaultEnvironmentKeyHash" type="uint32">
            <Row value="0xb134198a" />
        </Column>
        <Column name="TriggerObjectNameHash" type="uint32">
            <Row value="0xa86d94ef" />
        </Column>
        <Column name="0x1feb495e" type="uint32">
            <Row value="0xa86d94ef" />
        </Column>
    </Object>
    <Object version="0" name="EM3TimelineResourceKeeper［基本］" type="TypeInfo::Object::ResourceKeeper">
        <Column name="ResourceNameHashArray" type="uint32">
            <Row value="0x343f5b89" />
            <Row value="0xdb531b28" />
            <Row value="0x249527b4" />
            <Row value="0xa3c3caf1" />
            <Row value="0xdcc04d74" />
            <Row value="0x8f1c2d4e" />
        </Column>
    </Object>
</KidsObjDB>
