<?xml version="1.0" encoding="utf-8" ?>
<KidsObjDB version="0" platform="16" name_file="0x096f8896">
    <Object version="0" name="0x16cb4391" parent_object_file="0xcbe4a48c" parent_object="0x1c809afd">
        <Column name="WorldPosition" type="float">
            <Row value="0.0" />
            <Row value="0.0" />
            <Row value="0.0" />
        </Column>
        <Column name="WorldScale" type="float">
            <Row value="1.0" />
            <Row value="1.0" />
            <Row value="1.0" />
        </Column>
    </Object>
    <Object version="0" name="0x348291cb" type="0x1a83479f">
        <Column name="FieldSize" type="uint32">
            <Row value="0x0001f400" />
            <Row value="0x0001f400" />
        </Column>
        <Column name="FieldOffset" type="uint32">
            <Row value="0x00000000" />
            <Row value="0x00000000" />
        </Column>
        <Column name="0x6f1ab58b" type="uint32">
            <Row value="0x00000400" />
            <Row value="0x00000400" />
        </Column>
        <Column name="NumBlocks" type="uint32">
            <Row value="0x00000100" />
            <Row value="0x00000100" />
        </Column>
        <Column name="0x79c02ffe" type="uint32">
            <Row value="0x000186a0" />
        </Column>
        <Column name="0xa2dd60a1" type="uint32">
            <Row value="0x0001d4c0" />
        </Column>
        <Column name="0xe9567eeb" type="uint32">
            <Row value="0x00000001" />
            <Row value="0x00000000" />
            <Row value="0x00000000" />
            <Row value="0x00000000" />
            <Row value="0x00000000" />
            <Row value="0x00000001" />
            <Row value="0x00000001" />
            <Row value="0x00000000" />
            <Row value="0x00000000" />
            <Row value="0x00000000" />
            <Row value="0x00000001" />
            <Row value="0x00000002" />
            <Row value="0x00000000" />
            <Row value="0x00000000" />
            <Row value="0x00000000" />
            <Row value="0x00000002" />
            <Row value="0x00000003" />
            <Row value="0x00000004" />
            <Row value="0x00000000" />
            <Row value="0x00000000" />
            <Row value="0x00000000" />
            <Row value="0x00000002" />
            <Row value="0x00000005" />
            <Row value="0x00000006" />
            <Row value="0x00000000" />
            <Row value="0x00000000" />
            <Row value="0x00000000" />
            <Row value="0x00000001" />
            <Row value="0x00000007" />
            <Row value="0x00000000" />
            <Row value="0x00000000" />
            <Row value="0x00000000" />
            <Row value="0x00000001" />
            <Row value="0x00000008" />
            <Row value="0x00000000" />
            <Row value="0x00000000" />
            <Row value="0x00000000" />
            <Row value="0x00000001" />
            <Row value="0x00000009" />
            <Row value="0x00000000" />
            <Row value="0x00000000" />
            <Row value="0x00000000" />
        </Column>
        <Column name="0x7c441a6e" type="uint32">
            <Row value="0x00000001" />
            <Row value="0x00000000" />
            <Row value="0x00000000" />
            <Row value="0x00000000" />
            <Row value="0x00000003" />
            <Row value="0x00000001" />
            <Row value="0x00000002" />
            <Row value="0x00000003" />
            <Row value="0x00000000" />
            <Row value="0x00000000" />
            <Row value="0x00000001" />
            <Row value="0x00000004" />
            <Row value="0x00000000" />
            <Row value="0x00000000" />
            <Row value="0x00000001" />
            <Row value="0x00000005" />
            <Row value="0x00000000" />
            <Row value="0x00000000" />
            <Row value="0x00000001" />
            <Row value="0x00000006" />
            <Row value="0x00000000" />
            <Row value="0x00000000" />
            <Row value="0x00000001" />
            <Row value="0x00000007" />
            <Row value="0x00000000" />
            <Row value="0x00000000" />
            <Row value="0x00000001" />
            <Row value="0x00000008" />
            <Row value="0x00000000" />
            <Row value="0x00000000" />
            <Row value="0x00000001" />
            <Row value="0x00000009" />
            <Row value="0x00000000" />
            <Row value="0x00000000" />
            <Row value="0x00000001" />
            <Row value="0x0000000a" />
            <Row value="0x00000000" />
            <Row value="0x00000000" />
            <Row value="0x00000001" />
            <Row value="0x0000000b" />
            <Row value="0x00000000" />
            <Row value="0x00000000" />
        </Column>
        <Column name="ElementInfoArray" type="float">
            <Row value="1.20000005" />
            <Row value="0.800000012" />
            <Row value="1.20000005" />
            <Row value="0.0" />
            <Row value="0.0" />
            <Row value="0.0" />
            <Row value="0.0" />
            <Row value="0.0" />
            <Row value="0.0" />
            <Row value="0.0399999991" />
            <Row value="0.800000012" />
            <Row value="1.20000005" />
            <Row value="0.0" />
            <Row value="0.0" />
            <Row value="0.0" />
            <Row value="0.0" />
            <Row value="0.0" />
            <Row value="0.0" />
            <Row value="0.5" />
            <Row value="0.800000012" />
            <Row value="1.20000005" />
            <Row value="0.0" />
            <Row value="0.0" />
            <Row value="0.0" />
            <Row value="0.0" />
            <Row value="0.0" />
            <Row value="0.0" />
            <Row value="0.0500000007" />
            <Row value="0.800000012" />
            <Row value="1.20000005" />
            <Row value="0.0" />
            <Row value="0.0" />
            <Row value="0.0" />
            <Row value="0.0" />
            <Row value="0.0" />
            <Row value="0.0" />
            <Row value="0.200000003" />
            <Row value="0.800000012" />
            <Row value="1.20000005" />
            <Row value="0.0" />
            <Row value="0.0" />
            <Row value="0.0" />
            <Row value="0.0" />
            <Row value="0.0" />
            <Row value="0.0" />
            <Row value="0.200000003" />
            <Row value="1.0" />
            <Row value="1.0" />
            <Row value="0.0" />
            <Row value="0.0" />
            <Row value="0.0" />
            <Row value="0.0" />
            <Row value="0.0" />
            <Row value="0.0" />
            <Row value="0.0500000007" />
            <Row value="0.800000012" />
            <Row value="1.20000005" />
            <Row value="0.0" />
            <Row value="0.0" />
            <Row value="0.0" />
            <Row value="0.0" />
            <Row value="0.0" />
            <Row value="0.0" />
            <Row value="0.600000024" />
            <Row value="0.200000003" />
            <Row value="0.5" />
            <Row value="0.0" />
            <Row value="0.0" />
            <Row value="0.0" />
            <Row value="0.0" />
            <Row value="0.0" />
            <Row value="0.0" />
            <Row value="0.0500000007" />
            <Row value="0.400000006" />
            <Row value="0.5" />
            <Row value="0.0" />
            <Row value="0.0" />
            <Row value="0.0" />
            <Row value="0.0" />
            <Row value="0.0" />
            <Row value="0.0" />
            <Row value="0.800000012" />
            <Row value="0.800000012" />
            <Row value="1.20000005" />
            <Row value="0.0" />
            <Row value="0.0" />
            <Row value="0.0" />
            <Row value="0.0" />
            <Row value="0.0" />
            <Row value="0.0" />
            <Row value="0.5" />
            <Row value="0.800000012" />
            <Row value="1.20000005" />
            <Row value="0.0" />
            <Row value="0.0" />
            <Row value="0.0" />
            <Row value="0.0" />
            <Row value="0.0" />
            <Row value="0.0" />
            <Row value="1.0" />
            <Row value="1.0" />
            <Row value="1.0" />
            <Row value="0.0" />
            <Row value="0.0" />
            <Row value="0.0" />
            <Row value="0.0" />
            <Row value="0.0" />
            <Row value="0.0" />
        </Column>
        <Column name="ElementTypeArray" type="uint32">
            <Row value="0x00000000" />
            <Row value="0x00000000" />
            <Row value="0x00000000" />
            <Row value="0x00000000" />
            <Row value="0x00000000" />
            <Row value="0x00000000" />
            <Row value="0x00000000" />
            <Row value="0x00000000" />
            <Row value="0x00000000" />
            <Row value="0x00000000" />
            <Row value="0x00000000" />
            <Row value="0x00000000" />
        </Column>
        <Column name="0x5c9ee311" type="uint32">
            <Row value="0x00000019" />
            <Row value="0x00000019" />
            <Row value="0x00000019" />
            <Row value="0x00000019" />
            <Row value="0x00000019" />
            <Row value="0x00000019" />
            <Row value="0x00000019" />
            <Row value="0x00000019" />
            <Row value="0x00000019" />
            <Row value="0x00000019" />
            <Row value="0x00000019" />
            <Row value="0x00000000" />
        </Column>
        <Column name="0xe3c9c8f0" type="uint32">
            <Row value="0xdab09cc5" />
            <Row value="0x82955e12" />
            <Row value="0xa8296713" />
            <Row value="0xb06df871" />
            <Row value="0xf3301f4a" />
            <Row value="0xab824671" />
            <Row value="0x64f9d410" />
            <Row value="0x859d1af3" />
            <Row value="0xbf67bcd2" />
            <Row value="0x16cb4391" />
            <Row value="0x67d19416" />
            <Row value="0x82955e12" />
        </Column>
        <Column name="DisplaySetNameHashArray" type="uint32">
            <Row value="0xdab09cc5" />
            <Row value="0x82955e12" />
            <Row value="0xa8296713" />
            <Row value="0xb06df871" />
            <Row value="0xf3301f4a" />
            <Row value="0xab824671" />
            <Row value="0x64f9d410" />
            <Row value="0x67d19416" />
            <Row value="0x16cb4391" />
            <Row value="0x859d1af3" />
            <Row value="0xbf67bcd2" />
        </Column>
        <Column name="DensityMap" type="float" />
        <Column name="0x4cacd9fb" type="float" />
        <Column name="ResourceMap" type="uint8">
            <Rows binary="0x348291cb_ResourceMap.bin" />
        </Column>
        <Column name="0xe065f0e9" type="uint32">
            <Row value="0x00000542" />
            <Row value="0x0000083a" />
            <Row value="0x00000dff" />
            <Row value="0x00000a89" />
            <Row value="0x00001e28" />
            <Row value="0x000001d8" />
            <Row value="0x0000075e" />
            <Row value="0x0000113c" />
            <Row value="0x00000a4d" />
            <Row value="0x00001939" />
            <Row value="0x000022b0" />
            <Row value="0x00001c3f" />
        </Column>
        <Column name="0x711a5f43" type="uint8">
            <Row value="0x01" />
            <Row value="0x01" />
            <Row value="0x01" />
            <Row value="0x01" />
            <Row value="0x01" />
            <Row value="0x01" />
            <Row value="0x01" />
            <Row value="0x01" />
            <Row value="0x01" />
            <Row value="0x01" />
            <Row value="0x01" />
        </Column>
        <Column name="0x0fd0f003" type="float">
            <Row value="3000.0" />
            <Row value="3000.0" />
            <Row value="5500.0" />
            <Row value="6500.0" />
            <Row value="2500.0" />
            <Row value="4000.0" />
            <Row value="4000.0" />
            <Row value="4000.0" />
            <Row value="2500.0" />
            <Row value="40000.0" />
            <Row value="40000.0" />
            <Row value="40000.0" />
            <Row value="2500.0" />
            <Row value="4000.0" />
            <Row value="4000.0" />
            <Row value="4000.0" />
            <Row value="2500.0" />
            <Row value="4000.0" />
            <Row value="4000.0" />
            <Row value="4000.0" />
            <Row value="2500.0" />
            <Row value="4000.0" />
            <Row value="4000.0" />
            <Row value="4000.0" />
            <Row value="2500.0" />
            <Row value="4000.0" />
            <Row value="4000.0" />
            <Row value="4000.0" />
            <Row value="2000.0" />
            <Row value="3000.0" />
            <Row value="3000.0" />
            <Row value="3000.0" />
            <Row value="2000.0" />
            <Row value="3000.0" />
            <Row value="3000.0" />
            <Row value="3000.0" />
            <Row value="2500.0" />
            <Row value="4000.0" />
            <Row value="4000.0" />
            <Row value="4000.0" />
            <Row value="2500.0" />
            <Row value="4000.0" />
            <Row value="4000.0" />
            <Row value="4000.0" />
            <Row value="0.0" />
            <Row value="0.0" />
            <Row value="0.0" />
            <Row value="0.0" />
        </Column>
        <Column name="0x4b80cfb1" type="uint32">
            <Row value="0x00000001" />
        </Column>
        <Column name="0xa3dae7da" type="uint32">
            <Row value="0x0000c350" />
        </Column>
        <Column name="0xdd5651bc" type="uint32">
            <Row value="0x00000000" />
        </Column>
        <Column name="ScaleMap" type="float" />
        <Column name="0x8f049719" type="float" />
        <Column name="0xdd271667" type="uint32">
            <Row value="0x00002710" />
        </Column>
        <Column name="0xf709a219" type="uint32">
            <Row value="0x00002710" />
        </Column>
        <Column name="0xd25c3aa6" type="uint32">
            <Row value="0xdab09cc5" />
            <Row value="0x0000c350" />
            <Row value="0x0000c350" />
            <Row value="0x000061a8" />
            <Row value="0x0000c350" />
            <Row value="0x00000018" />
            <Row value="0x00000013" />
            <Row value="0x82955e12" />
            <Row value="0x0000c350" />
            <Row value="0x0000c350" />
            <Row value="0x0000c350" />
            <Row value="0x0000c350" />
            <Row value="0x0000c350" />
            <Row value="0x0000c350" />
            <Row value="0xa8296713" />
            <Row value="0x0000c350" />
            <Row value="0x0000c350" />
            <Row value="0x0000c350" />
            <Row value="0x0000c350" />
            <Row value="0x0000c350" />
            <Row value="0x0000c350" />
            <Row value="0xb06df871" />
            <Row value="0x0000c350" />
            <Row value="0x0000c350" />
            <Row value="0x0000c350" />
            <Row value="0x0000c350" />
            <Row value="0x0000c350" />
            <Row value="0x0000c350" />
            <Row value="0xf3301f4a" />
            <Row value="0x0000c350" />
            <Row value="0x0000c350" />
            <Row value="0x0000c350" />
            <Row value="0x0000c350" />
            <Row value="0x0000c350" />
            <Row value="0x0000c350" />
            <Row value="0xab824671" />
            <Row value="0x0000c350" />
            <Row value="0x0000c350" />
            <Row value="0x0000c350" />
            <Row value="0x0000c350" />
            <Row value="0x0000c350" />
            <Row value="0x0000c350" />
            <Row value="0x64f9d410" />
            <Row value="0x0000c350" />
            <Row value="0x0000c350" />
            <Row value="0x0000c350" />
            <Row value="0x0000c350" />
            <Row value="0x0000c350" />
            <Row value="0x0000c350" />
            <Row value="0x67d19416" />
            <Row value="0x0000c350" />
            <Row value="0x0000c350" />
            <Row value="0x0000c350" />
            <Row value="0x0000c350" />
            <Row value="0x0000c350" />
            <Row value="0x0000c350" />
            <Row value="0x16cb4391" />
            <Row value="0x0000c350" />
            <Row value="0x0000c350" />
            <Row value="0x0000c350" />
            <Row value="0x0000c350" />
            <Row value="0x0000c350" />
            <Row value="0x0000c350" />
            <Row value="0x859d1af3" />
            <Row value="0x0000c350" />
            <Row value="0x0000c350" />
            <Row value="0x0000c350" />
            <Row value="0x0000c350" />
            <Row value="0x0000c350" />
            <Row value="0x0000c350" />
            <Row value="0xbf67bcd2" />
            <Row value="0x0000c350" />
            <Row value="0x0000c350" />
            <Row value="0x0000c350" />
            <Row value="0x0000c350" />
            <Row value="0x0000c350" />
            <Row value="0x0000c350" />
        </Column>
    </Object>
    <Object version="0" name="0x64f9d410" parent_object_file="0xcbe4a48c" parent_object="0xd64e4024">
        <Column name="WorldPosition" type="float">
            <Row value="0.0" />
            <Row value="0.0" />
            <Row value="0.0" />
        </Column>
        <Column name="WorldScale" type="float">
            <Row value="1.0" />
            <Row value="1.0" />
            <Row value="1.0" />
        </Column>
    </Object>
    <Object version="0" name="0x67d19416" parent_object_file="0xcbe4a48c" parent_object="0x84538182">
        <Column name="WorldPosition" type="float">
            <Row value="0.0" />
            <Row value="0.0" />
            <Row value="0.0" />
        </Column>
        <Column name="WorldScale" type="float">
            <Row value="1.0" />
            <Row value="1.0" />
            <Row value="1.0" />
        </Column>
    </Object>
    <Object version="0" name="0x82955e12" parent_object_file="0xcbe4a48c" parent_object="0xf07f1526">
        <Column name="WorldPosition" type="float">
            <Row value="0.0" />
            <Row value="0.0" />
            <Row value="0.0" />
        </Column>
        <Column name="WorldScale" type="float">
            <Row value="1.0" />
            <Row value="1.0" />
            <Row value="1.0" />
        </Column>
    </Object>
    <Object version="0" name="0x859d1af3" parent_object_file="0xcbe4a48c" parent_object="0x89595d5f">
        <Column name="WorldPosition" type="float">
            <Row value="0.0" />
            <Row value="0.0" />
            <Row value="0.0" />
        </Column>
        <Column name="WorldScale" type="float">
            <Row value="1.0" />
            <Row value="1.0" />
            <Row value="1.0" />
        </Column>
    </Object>
    <Object version="0" name="0xa8296713" parent_object_file="0xcbe4a48c" parent_object="0x16131e27">
        <Column name="WorldPosition" type="float">
            <Row value="0.0" />
            <Row value="0.0" />
            <Row value="0.0" />
        </Column>
        <Column name="WorldScale" type="float">
            <Row value="1.0" />
            <Row value="1.0" />
            <Row value="1.0" />
        </Column>
    </Object>
    <Object version="0" name="0xab824671" parent_object_file="0xcbe4a48c" parent_object="0x1cd6b285">
        <Column name="WorldPosition" type="float">
            <Row value="0.0" />
            <Row value="0.0" />
            <Row value="0.0" />
        </Column>
        <Column name="WorldScale" type="float">
            <Row value="1.0" />
            <Row value="1.0" />
            <Row value="1.0" />
        </Column>
    </Object>
    <Object version="0" name="0xb06df871" parent_object_file="0xcbe4a48c" parent_object="0x1e57af85">
        <Column name="WorldPosition" type="float">
            <Row value="0.0" />
            <Row value="0.0" />
            <Row value="0.0" />
        </Column>
        <Column name="WorldScale" type="float">
            <Row value="1.0" />
            <Row value="1.0" />
            <Row value="1.0" />
        </Column>
    </Object>
    <Object version="0" name="0xbf67bcd2" parent_object_file="0xcbe4a48c" parent_object="0xc323ff3e">
        <Column name="WorldPosition" type="float">
            <Row value="0.0" />
            <Row value="0.0" />
            <Row value="0.0" />
        </Column>
        <Column name="WorldScale" type="float">
            <Row value="1.0" />
            <Row value="1.0" />
            <Row value="1.0" />
        </Column>
    </Object>
    <Object version="0" name="0xdab09cc5" parent_object_file="0xcbe4a48c" parent_object="0x4b66f531">
        <Column name="WorldPosition" type="float">
            <Row value="0.0" />
            <Row value="0.0" />
            <Row value="0.0" />
        </Column>
        <Column name="WorldScale" type="float">
            <Row value="1.0" />
            <Row value="1.0" />
            <Row value="1.0" />
        </Column>
    </Object>
    <Object version="0" name="0xf3301f4a" parent_object_file="0xcbe4a48c" parent_object="0x9944d45e">
        <Column name="WorldPosition" type="float">
            <Row value="0.0" />
            <Row value="0.0" />
            <Row value="0.0" />
        </Column>
        <Column name="WorldScale" type="float">
            <Row value="1.0" />
            <Row value="1.0" />
            <Row value="1.0" />
        </Column>
    </Object>
</KidsObjDB>
