<?xml version="1.0" encoding="utf-8" ?>
<KidsObjDB version="0" platform="16" name_file="0xe86e0640">
    <Object version="0" name="0x04b5399c" parent_object_file="Field_Common.kidsobjdb" parent_object="FE4SoundPlaceableEmitterBox［Basic］">
        <Column name="WorldScale" type="float">
            <Row value="1800.0" />
            <Row value="4000.0" />
            <Row value="100.0" />
        </Column>
        <Column name="WorldPosition" type="float">
            <Row value="74927.1094" />
            <Row value="17328.4688" />
            <Row value="32129.1855" />
        </Column>
        <Column name="WorldQuaternion" type="float">
            <Row value="0.306165218" />
            <Row value="0.156834871" />
            <Row value="0.0119019048" />
            <Row value="0.938894033" />
        </Column>
        <Column name="BankObjectNameHash" type="uint32">
            <Row value="0x9f329e28" />
        </Column>
        <Column name="ProgId" type="uint32">
            <Row value="0x4dba9bb1" />
        </Column>
    </Object>
    <Object version="0" name="0x28f3bddb" parent_object_file="Field_Common.kidsobjdb" parent_object="FE4SoundPlaceableEmitterBox［Basic］">
        <Column name="WorldScale" type="float">
            <Row value="500.0" />
            <Row value="2500.0" />
            <Row value="1500.0" />
        </Column>
        <Column name="WorldPosition" type="float">
            <Row value="92594.8828" />
            <Row value="19467.2637" />
            <Row value="92734.0938" />
        </Column>
        <Column name="WorldQuaternion" type="float">
            <Row value="-0.0936259776" />
            <Row value="-0.3268525" />
            <Row value="0.258967608" />
            <Row value="0.904067218" />
        </Column>
        <Column name="BankObjectNameHash" type="uint32">
            <Row value="0x9f329e28" />
        </Column>
        <Column name="ProgId" type="uint32">
            <Row value="0x4dba9bb1" />
        </Column>
    </Object>
    <Object version="0" name="0x319d9123" type="TypeInfo::Object::Sound::ReverbSetting">
        <Column name="DefaultPresetNameHash" type="uint32">
            <Row value="0x4a050832" />
        </Column>
        <Column name="DefaultVolume" type="float">
            <Row value="1.0" />
        </Column>
        <Column name="DefaultFadeTime" type="int32">
            <Row value="0" />
        </Column>
    </Object>
    <Object version="0" name="0x4a050832" type="TypeInfo::Object::Sound::ReverbPreset">
        <Column name="Room" type="float">
            <Row value="-10000.0" />
        </Column>
        <Column name="RoomHF" type="float">
            <Row value="0.0" />
        </Column>
        <Column name="DecayTime" type="float">
            <Row value="1.0" />
        </Column>
        <Column name="DecayHFRatio" type="float">
            <Row value="0.5" />
        </Column>
        <Column name="Reflections" type="float">
            <Row value="-10000.0" />
        </Column>
        <Column name="ReflectionsDelay" type="float">
            <Row value="0.0199999996" />
        </Column>
        <Column name="Reverb" type="float">
            <Row value="-10000.0" />
        </Column>
        <Column name="ReverbDelay" type="float">
            <Row value="0.0399999991" />
        </Column>
        <Column name="Diffusion" type="float">
            <Row value="100.0" />
        </Column>
        <Column name="Density" type="float">
            <Row value="100.0" />
        </Column>
        <Column name="HFReference" type="float">
            <Row value="5000.0" />
        </Column>
    </Object>
    <Object version="0" name="0x5e464a2b" type="TypeInfo::Object::Sound::AmbientSetting">
        <Column name="BankObjectNameHash0" type="uint32">
            <Row value="0x9f329e28" />
        </Column>
        <Column name="ProgId0" type="uint32">
            <Row value="0x69fe83e4" />
        </Column>
        <Column name="UseAmbientOcc0" type="uint8">
            <Row value="0x00" />
        </Column>
        <Column name="UseSmoothOcc0" type="uint8">
            <Row value="0x00" />
        </Column>
        <Column name="OccRegionIndexArray0" type="uint32">
            <Row value="0x00000000" />
            <Row value="0x00000000" />
            <Row value="0x00000000" />
            <Row value="0x00000000" />
            <Row value="0x00000000" />
            <Row value="0x00000000" />
            <Row value="0x00000000" />
            <Row value="0x00000000" />
        </Column>
        <Column name="BankObjectNameHash1" type="uint32">
            <Row value="0x00000000" />
        </Column>
        <Column name="ProgId1" type="uint32">
            <Row value="0x00000000" />
        </Column>
        <Column name="UseAmbientOcc1" type="uint8">
            <Row value="0x00" />
        </Column>
        <Column name="UseSmoothOcc1" type="uint8">
            <Row value="0x00" />
        </Column>
        <Column name="OccRegionIndexArray1" type="uint32">
            <Row value="0x00000000" />
            <Row value="0x00000000" />
            <Row value="0x00000000" />
            <Row value="0x00000000" />
            <Row value="0x00000000" />
            <Row value="0x00000000" />
            <Row value="0x00000000" />
            <Row value="0x00000000" />
        </Column>
        <Column name="BankObjectNameHash2" type="uint32">
            <Row value="0x00000000" />
        </Column>
        <Column name="ProgId2" type="uint32">
            <Row value="0x00000000" />
        </Column>
        <Column name="UseAmbientOcc2" type="uint8">
            <Row value="0x00" />
        </Column>
        <Column name="UseSmoothOcc2" type="uint8">
            <Row value="0x00" />
        </Column>
        <Column name="OccRegionIndexArray2" type="uint32">
            <Row value="0x00000000" />
            <Row value="0x00000000" />
            <Row value="0x00000000" />
            <Row value="0x00000000" />
            <Row value="0x00000000" />
            <Row value="0x00000000" />
            <Row value="0x00000000" />
            <Row value="0x00000000" />
        </Column>
        <Column name="BankObjectNameHash3" type="uint32">
            <Row value="0x00000000" />
        </Column>
        <Column name="ProgId3" type="uint32">
            <Row value="0x00000000" />
        </Column>
        <Column name="UseAmbientOcc3" type="uint8">
            <Row value="0x00" />
        </Column>
        <Column name="UseSmoothOcc3" type="uint8">
            <Row value="0x00" />
        </Column>
        <Column name="OccRegionIndexArray3" type="uint32">
            <Row value="0x00000000" />
            <Row value="0x00000000" />
            <Row value="0x00000000" />
            <Row value="0x00000000" />
            <Row value="0x00000000" />
            <Row value="0x00000000" />
            <Row value="0x00000000" />
            <Row value="0x00000000" />
        </Column>
        <Column name="GateSwitchIndexArray0" type="uint32">
            <Row value="0x00000000" />
            <Row value="0x00000000" />
            <Row value="0x00000000" />
            <Row value="0x00000000" />
            <Row value="0x00000000" />
            <Row value="0x00000000" />
            <Row value="0x00000000" />
            <Row value="0x00000000" />
        </Column>
        <Column name="GateSwitchIndexArray1" type="uint32">
            <Row value="0x00000000" />
            <Row value="0x00000000" />
            <Row value="0x00000000" />
            <Row value="0x00000000" />
            <Row value="0x00000000" />
            <Row value="0x00000000" />
            <Row value="0x00000000" />
            <Row value="0x00000000" />
        </Column>
        <Column name="GateSwitchIndexArray2" type="uint32">
            <Row value="0x00000000" />
            <Row value="0x00000000" />
            <Row value="0x00000000" />
            <Row value="0x00000000" />
            <Row value="0x00000000" />
            <Row value="0x00000000" />
            <Row value="0x00000000" />
            <Row value="0x00000000" />
        </Column>
        <Column name="GateSwitchIndexArray3" type="uint32">
            <Row value="0x00000000" />
            <Row value="0x00000000" />
            <Row value="0x00000000" />
            <Row value="0x00000000" />
            <Row value="0x00000000" />
            <Row value="0x00000000" />
            <Row value="0x00000000" />
            <Row value="0x00000000" />
        </Column>
    </Object>
    <Object version="0" name="0xd86f31a6" parent_object_file="Field_Common.kidsobjdb" parent_object="FE4SoundPlaceableEmitterPrism［Basic］">
        <Column name="WorldScale" type="float">
            <Row value="300.0" />
            <Row value="100.0" />
            <Row value="10.0" />
        </Column>
        <Column name="WorldPosition" type="float">
            <Row value="46652.9258" />
            <Row value="23825.4297" />
            <Row value="60485.0391" />
        </Column>
        <Column name="WorldQuaternion" type="float">
            <Row value="-0.245800614" />
            <Row value="-0.63099587" />
            <Row value="-0.270928741" />
            <Row value="0.684123039" />
        </Column>
        <Column name="Height" type="float">
            <Row value="99.9999771" />
        </Column>
        <Column name="PositionArray" type="float">
            <Row value="66.7379532" />
            <Row value="-50.0" />
            <Row value="-30.2084694" />
            <Row value="50.0" />
            <Row value="-50.0" />
            <Row value="-50.0" />
            <Row value="-17.2428799" />
            <Row value="-50.0" />
            <Row value="-49.9993401" />
            <Row value="-95.3281631" />
            <Row value="-50.0" />
            <Row value="-5030.86523" />
            <Row value="-59.6986389" />
            <Row value="-50.0" />
            <Row value="-1037.12097" />
            <Row value="-58.4327393" />
            <Row value="-50.0" />
            <Row value="-895.228699" />
            <Row value="-50.0" />
            <Row value="-50.0" />
            <Row value="50.0" />
        </Column>
        <Column name="BankObjectNameHash" type="uint32">
            <Row value="0x9f329e28" />
        </Column>
        <Column name="ProgId" type="uint32">
            <Row value="0x4dba9bb1" />
        </Column>
    </Object>
    <Object version="0" name="0xe71da225" parent_object_file="Field_Common.kidsobjdb" parent_object="FE4SoundPlaceableEmitterPrism［Basic］">
        <Column name="WorldScale" type="float">
            <Row value="100.0" />
            <Row value="50.0" />
            <Row value="100.0" />
        </Column>
        <Column name="WorldPosition" type="float">
            <Row value="48577.2227" />
            <Row value="15000.0" />
            <Row value="92699.8047" />
        </Column>
        <Column name="WorldQuaternion" type="float">
            <Row value="-0.0386870354" />
            <Row value="0.00201029028" />
            <Row value="0.0526614264" />
            <Row value="0.99786073" />
        </Column>
        <Column name="PositionArray" type="float">
            <Row value="176.838699" />
            <Row value="-50.0" />
            <Row value="92.2975769" />
            <Row value="50.0" />
            <Row value="-50.0" />
            <Row value="-50.0" />
            <Row value="-50.0" />
            <Row value="-50.0" />
            <Row value="-50.0" />
            <Row value="-50.0" />
            <Row value="-50.0" />
            <Row value="50.0" />
            <Row value="-74.404007" />
            <Row value="-50.0" />
            <Row value="112.993698" />
            <Row value="0.800507784" />
            <Row value="-50.0" />
            <Row value="50.0" />
            <Row value="41.8125381" />
            <Row value="-50.0" />
            <Row value="50.0" />
        </Column>
        <Column name="BankObjectNameHash" type="uint32">
            <Row value="0x9f329e28" />
        </Column>
        <Column name="ProgId" type="uint32">
            <Row value="0x4dba9bb1" />
        </Column>
    </Object>
</KidsObjDB>
