<?xml version="1.0" encoding="utf-8" ?>
<KidsObjDB version="0" platform="16" name_file="0x47fbfa70">
    <Object version="0" name="0x011f96ab" parent_object_file="Field_Common.kidsobjdb" parent_object="FE4SoundPlaceableEmitterBox［Basic］">
        <Column name="WorldScale" type="float">
            <Row value="339.058624" />
            <Row value="1200.0" />
            <Row value="233.054718" />
        </Column>
        <Column name="WorldPosition" type="float">
            <Row value="71832.9297" />
            <Row value="37080.7695" />
            <Row value="75975.2422" />
        </Column>
        <Column name="WorldQuaternion" type="float">
            <Row value="0.0" />
            <Row value="0.0" />
            <Row value="0.0" />
            <Row value="1.0" />
        </Column>
        <Column name="BankObjectNameHash" type="uint32">
            <Row value="0x9f329e28" />
        </Column>
        <Column name="ProgId" type="uint32">
            <Row value="0x52223abd" />
        </Column>
        <Column name="Level" type="float">
            <Row value="0.766666651" />
        </Column>
    </Object>
    <Object version="0" name="0x0a979048" parent_object_file="Field_Common.kidsobjdb" parent_object="FE4SoundPlaceableEmitterLine［Basic］">
        <Column name="WorldScale" type="float">
            <Row value="1.0" />
            <Row value="1.0" />
            <Row value="1.0" />
        </Column>
        <Column name="WorldPosition" type="float">
            <Row value="39339.4727" />
            <Row value="20318.9941" />
            <Row value="98836.6641" />
        </Column>
        <Column name="WorldQuaternion" type="float">
            <Row value="0.675429463" />
            <Row value="-0.233250096" />
            <Row value="-0.240141556" />
            <Row value="0.657054782" />
        </Column>
        <Column name="PositionArray" type="float">
            <Row value="50.0" />
            <Row value="0.0" />
            <Row value="50.0" />
            <Row value="-399.183594" />
            <Row value="-15.5468798" />
            <Row value="-484.335907" />
        </Column>
        <Column name="SegmentIndexArray" type="uint32">
            <Row value="0x00000000" />
            <Row value="0x00000001" />
        </Column>
        <Column name="BankObjectNameHash" type="uint32">
            <Row value="0x9f329e28" />
        </Column>
        <Column name="ProgId" type="uint32">
            <Row value="0x52223abd" />
        </Column>
        <Column name="Tune" type="float">
            <Row value="-200.0" />
        </Column>
    </Object>
    <Object version="0" name="0x27160dcc" parent_object_file="Field_Common.kidsobjdb" parent_object="FE4SoundPlaceableEmitterLine［Basic］">
        <Column name="WorldScale" type="float">
            <Row value="0.314797729" />
            <Row value="0.314797729" />
            <Row value="1.0" />
        </Column>
        <Column name="WorldPosition" type="float">
            <Row value="35403.9141" />
            <Row value="21555.3555" />
            <Row value="83418.0313" />
        </Column>
        <Column name="WorldQuaternion" type="float">
            <Row value="-0.109663256" />
            <Row value="0.213261247" />
            <Row value="-0.886135459" />
            <Row value="-0.396557093" />
        </Column>
        <Column name="PositionArray" type="float">
            <Row value="-6701.52295" />
            <Row value="-2300.25" />
            <Row value="-47.5156288" />
            <Row value="-21410.5703" />
            <Row value="24065.7207" />
            <Row value="-16107.0195" />
        </Column>
        <Column name="SegmentIndexArray" type="uint32">
            <Row value="0x00000000" />
            <Row value="0x00000001" />
        </Column>
        <Column name="BankObjectNameHash" type="uint32">
            <Row value="0x9f329e28" />
        </Column>
        <Column name="ProgId" type="uint32">
            <Row value="0x52223abd" />
        </Column>
    </Object>
    <Object version="0" name="0x2a0ded77" parent_object_file="Field_Common.kidsobjdb" parent_object="FE4SoundPlaceableEmitterPrism［Basic］">
        <Column name="WorldScale" type="float">
            <Row value="100.0" />
            <Row value="250.0" />
            <Row value="50.0" />
        </Column>
        <Column name="WorldPosition" type="float">
            <Row value="98050.8281" />
            <Row value="28000.0" />
            <Row value="48029.3516" />
        </Column>
        <Column name="WorldQuaternion" type="float">
            <Row value="0.0" />
            <Row value="0.0" />
            <Row value="0.0" />
            <Row value="1.0" />
        </Column>
        <Column name="PositionArray" type="float">
            <Row value="50.0" />
            <Row value="-50.0" />
            <Row value="50.0" />
            <Row value="50.0" />
            <Row value="-50.0" />
            <Row value="-50.0" />
            <Row value="-57.0359383" />
            <Row value="-50.0" />
            <Row value="-382.422302" />
            <Row value="-222.761795" />
            <Row value="-50.0" />
            <Row value="-70.310791" />
            <Row value="-50.0" />
            <Row value="-50.0" />
            <Row value="50.0" />
            <Row value="-140.735107" />
            <Row value="-50.0" />
            <Row value="204.056396" />
            <Row value="-346.636993" />
            <Row value="-50.0" />
            <Row value="135.930206" />
            <Row value="-380.213806" />
            <Row value="-50.0" />
            <Row value="-132.959702" />
            <Row value="-566.12738" />
            <Row value="-50.0" />
            <Row value="-635.991516" />
            <Row value="-709.701477" />
            <Row value="-50.0" />
            <Row value="-340.879395" />
            <Row value="-469.525299" />
            <Row value="-50.0" />
            <Row value="-261.931885" />
            <Row value="-388.025208" />
            <Row value="-50.0" />
            <Row value="-88.8167191" />
            <Row value="-423.306488" />
            <Row value="-50.0" />
            <Row value="110.562798" />
            <Row value="-464.866302" />
            <Row value="-50.0" />
            <Row value="269.064087" />
            <Row value="-416.74231" />
            <Row value="-50.0" />
            <Row value="372.348389" />
            <Row value="-321.965088" />
            <Row value="-50.0" />
            <Row value="457.137909" />
            <Row value="-149.269806" />
            <Row value="-50.0" />
            <Row value="411.997986" />
            <Row value="-71.1938171" />
            <Row value="-50.0" />
            <Row value="340.452911" />
            <Row value="-84.7131271" />
            <Row value="-50.0" />
            <Row value="682.986816" />
            <Row value="-139.635101" />
            <Row value="-50.0" />
            <Row value="798.355286" />
            <Row value="-38.6669502" />
            <Row value="-50.0" />
            <Row value="874.718079" />
            <Row value="-53.7493706" />
            <Row value="-50.0" />
            <Row value="649.335022" />
            <Row value="-11.9939098" />
            <Row value="-50.0" />
            <Row value="529.383423" />
            <Row value="25.9675007" />
            <Row value="-50.0" />
            <Row value="609.243408" />
            <Row value="68.58992" />
            <Row value="-50.0" />
            <Row value="607.145813" />
            <Row value="115.149101" />
            <Row value="-50.0" />
            <Row value="681.926575" />
            <Row value="136.054993" />
            <Row value="-50.0" />
            <Row value="666.846375" />
            <Row value="156.652603" />
            <Row value="-50.0" />
            <Row value="707.004517" />
            <Row value="110.8731" />
            <Row value="-50.0" />
            <Row value="848.65033" />
            <Row value="171.721802" />
            <Row value="-50.0" />
            <Row value="885.875793" />
            <Row value="174.328003" />
            <Row value="-50.0" />
            <Row value="766.671082" />
            <Row value="182.103806" />
            <Row value="-50.0" />
            <Row value="756.625305" />
            <Row value="230.583099" />
            <Row value="-50.0" />
            <Row value="721.762817" />
            <Row value="272.315613" />
            <Row value="-50.0" />
            <Row value="702.585022" />
            <Row value="298.689606" />
            <Row value="-50.0" />
            <Row value="712.922485" />
            <Row value="380.68399" />
            <Row value="-50.0" />
            <Row value="635.641296" />
            <Row value="344.898193" />
            <Row value="-50.0" />
            <Row value="571.344421" />
            <Row value="299.613007" />
            <Row value="-50.0" />
            <Row value="678.419189" />
            <Row value="236.313599" />
            <Row value="-50.0" />
            <Row value="660.007874" />
            <Row value="211.687302" />
            <Row value="-50.0" />
            <Row value="552.700378" />
            <Row value="176.767303" />
            <Row value="-50.0" />
            <Row value="585.185303" />
            <Row value="125.660103" />
            <Row value="-50.0" />
            <Row value="498.484589" />
            <Row value="78.4641418" />
            <Row value="-50.0" />
            <Row value="577.100586" />
            <Row value="33.9040604" />
            <Row value="-50.0" />
            <Row value="544.317627" />
            <Row value="52.1824989" />
            <Row value="-50.0" />
            <Row value="402.131714" />
            <Row value="1.494609" />
            <Row value="-50.0" />
            <Row value="400.7099" />
            <Row value="-21.7203903" />
            <Row value="-50.0" />
            <Row value="299.117096" />
            <Row value="47.9158592" />
            <Row value="-50.0" />
            <Row value="276.223785" />
            <Row value="283.536011" />
            <Row value="-50.0" />
            <Row value="621.073303" />
            <Row value="48.855629" />
            <Row value="-50.0" />
            <Row value="174.220901" />
        </Column>
        <Column name="BankObjectNameHash" type="uint32">
            <Row value="0x9f329e28" />
        </Column>
        <Column name="ProgId" type="uint32">
            <Row value="0xe75e195d" />
        </Column>
    </Object>
    <Object version="0" name="0x3dd40e3b" type="TypeInfo::Object::Sound::AmbientSetting">
        <Column name="BankObjectNameHash0" type="uint32">
            <Row value="0x9f329e28" />
        </Column>
        <Column name="ProgId0" type="uint32">
            <Row value="0x69fe83e4" />
        </Column>
        <Column name="UseAmbientOcc0" type="uint8">
            <Row value="0x00" />
        </Column>
        <Column name="UseSmoothOcc0" type="uint8">
            <Row value="0x00" />
        </Column>
        <Column name="OccRegionIndexArray0" type="uint32">
            <Row value="0x00000000" />
            <Row value="0x00000000" />
            <Row value="0x00000000" />
            <Row value="0x00000000" />
            <Row value="0x00000000" />
            <Row value="0x00000000" />
            <Row value="0x00000000" />
            <Row value="0x00000000" />
        </Column>
        <Column name="BankObjectNameHash1" type="uint32">
            <Row value="0x00000000" />
        </Column>
        <Column name="ProgId1" type="uint32">
            <Row value="0x00000000" />
        </Column>
        <Column name="UseAmbientOcc1" type="uint8">
            <Row value="0x00" />
        </Column>
        <Column name="UseSmoothOcc1" type="uint8">
            <Row value="0x00" />
        </Column>
        <Column name="OccRegionIndexArray1" type="uint32">
            <Row value="0x00000000" />
            <Row value="0x00000000" />
            <Row value="0x00000000" />
            <Row value="0x00000000" />
            <Row value="0x00000000" />
            <Row value="0x00000000" />
            <Row value="0x00000000" />
            <Row value="0x00000000" />
        </Column>
        <Column name="BankObjectNameHash2" type="uint32">
            <Row value="0x00000000" />
        </Column>
        <Column name="ProgId2" type="uint32">
            <Row value="0x00000000" />
        </Column>
        <Column name="UseAmbientOcc2" type="uint8">
            <Row value="0x00" />
        </Column>
        <Column name="UseSmoothOcc2" type="uint8">
            <Row value="0x00" />
        </Column>
        <Column name="OccRegionIndexArray2" type="uint32">
            <Row value="0x00000000" />
            <Row value="0x00000000" />
            <Row value="0x00000000" />
            <Row value="0x00000000" />
            <Row value="0x00000000" />
            <Row value="0x00000000" />
            <Row value="0x00000000" />
            <Row value="0x00000000" />
        </Column>
        <Column name="BankObjectNameHash3" type="uint32">
            <Row value="0x00000000" />
        </Column>
        <Column name="ProgId3" type="uint32">
            <Row value="0x00000000" />
        </Column>
        <Column name="UseAmbientOcc3" type="uint8">
            <Row value="0x00" />
        </Column>
        <Column name="UseSmoothOcc3" type="uint8">
            <Row value="0x00" />
        </Column>
        <Column name="OccRegionIndexArray3" type="uint32">
            <Row value="0x00000000" />
            <Row value="0x00000000" />
            <Row value="0x00000000" />
            <Row value="0x00000000" />
            <Row value="0x00000000" />
            <Row value="0x00000000" />
            <Row value="0x00000000" />
            <Row value="0x00000000" />
        </Column>
        <Column name="GateSwitchIndexArray0" type="uint32">
            <Row value="0x00000000" />
            <Row value="0x00000000" />
            <Row value="0x00000000" />
            <Row value="0x00000000" />
            <Row value="0x00000000" />
            <Row value="0x00000000" />
            <Row value="0x00000000" />
            <Row value="0x00000000" />
        </Column>
        <Column name="GateSwitchIndexArray1" type="uint32">
            <Row value="0x00000000" />
            <Row value="0x00000000" />
            <Row value="0x00000000" />
            <Row value="0x00000000" />
            <Row value="0x00000000" />
            <Row value="0x00000000" />
            <Row value="0x00000000" />
            <Row value="0x00000000" />
        </Column>
        <Column name="GateSwitchIndexArray2" type="uint32">
            <Row value="0x00000000" />
            <Row value="0x00000000" />
            <Row value="0x00000000" />
            <Row value="0x00000000" />
            <Row value="0x00000000" />
            <Row value="0x00000000" />
            <Row value="0x00000000" />
            <Row value="0x00000000" />
        </Column>
        <Column name="GateSwitchIndexArray3" type="uint32">
            <Row value="0x00000000" />
            <Row value="0x00000000" />
            <Row value="0x00000000" />
            <Row value="0x00000000" />
            <Row value="0x00000000" />
            <Row value="0x00000000" />
            <Row value="0x00000000" />
            <Row value="0x00000000" />
        </Column>
    </Object>
    <Object version="0" name="0x4a050832" type="TypeInfo::Object::Sound::ReverbPreset">
        <Column name="Room" type="float">
            <Row value="-10000.0" />
        </Column>
        <Column name="RoomHF" type="float">
            <Row value="0.0" />
        </Column>
        <Column name="DecayTime" type="float">
            <Row value="1.0" />
        </Column>
        <Column name="DecayHFRatio" type="float">
            <Row value="0.5" />
        </Column>
        <Column name="Reflections" type="float">
            <Row value="-10000.0" />
        </Column>
        <Column name="ReflectionsDelay" type="float">
            <Row value="0.0199999996" />
        </Column>
        <Column name="Reverb" type="float">
            <Row value="-10000.0" />
        </Column>
        <Column name="ReverbDelay" type="float">
            <Row value="0.0399999991" />
        </Column>
        <Column name="Diffusion" type="float">
            <Row value="100.0" />
        </Column>
        <Column name="Density" type="float">
            <Row value="100.0" />
        </Column>
        <Column name="HFReference" type="float">
            <Row value="5000.0" />
        </Column>
    </Object>
    <Object version="0" name="0x5ff66e6b" parent_object_file="Field_Common.kidsobjdb" parent_object="FE4SoundPlaceableEmitterLine［Basic］">
        <Column name="WorldScale" type="float">
            <Row value="1.0" />
            <Row value="1.0" />
            <Row value="1.0" />
        </Column>
        <Column name="WorldPosition" type="float">
            <Row value="48296.8086" />
            <Row value="31098.1895" />
            <Row value="39008.0117" />
        </Column>
        <Column name="WorldQuaternion" type="float">
            <Row value="-0.724179268" />
            <Row value="-0.0612644665" />
            <Row value="0.0648808479" />
            <Row value="0.68381393" />
        </Column>
        <Column name="PositionArray" type="float">
            <Row value="100.949203" />
            <Row value="57.8183594" />
            <Row value="842.324219" />
            <Row value="-236.289093" />
            <Row value="270.332001" />
            <Row value="-1144.05896" />
        </Column>
        <Column name="SegmentIndexArray" type="uint32">
            <Row value="0x00000000" />
            <Row value="0x00000001" />
        </Column>
        <Column name="BankObjectNameHash" type="uint32">
            <Row value="0x9f329e28" />
        </Column>
        <Column name="ProgId" type="uint32">
            <Row value="0x52223abd" />
        </Column>
    </Object>
    <Object version="0" name="0x603fd43e" parent_object_file="Field_Common.kidsobjdb" parent_object="FE4SoundPlaceableEmitterPrism［Basic］">
        <Column name="WorldScale" type="float">
            <Row value="54.0858002" />
            <Row value="183.891724" />
            <Row value="54.0858002" />
        </Column>
        <Column name="WorldPosition" type="float">
            <Row value="107445.0" />
            <Row value="25000.0" />
            <Row value="97767.7422" />
        </Column>
        <Column name="WorldQuaternion" type="float">
            <Row value="0.0" />
            <Row value="0.0" />
            <Row value="0.0" />
            <Row value="1.0" />
        </Column>
        <Column name="PositionArray" type="float">
            <Row value="50.0" />
            <Row value="-50.0" />
            <Row value="50.0" />
            <Row value="61.1772499" />
            <Row value="-50.0" />
            <Row value="-18.3142204" />
            <Row value="128.820602" />
            <Row value="-50.0" />
            <Row value="-84.2863464" />
            <Row value="72.9143982" />
            <Row value="-50.0" />
            <Row value="-90.0503693" />
            <Row value="-105.666" />
            <Row value="-50.0" />
            <Row value="-67.4089737" />
            <Row value="-50.0" />
            <Row value="-50.0" />
            <Row value="50.0" />
            <Row value="-24.8918705" />
            <Row value="-50.0" />
            <Row value="49.9999809" />
            <Row value="-20.5116806" />
            <Row value="-50.0" />
            <Row value="120.468002" />
            <Row value="17.9752007" />
            <Row value="-50.0" />
            <Row value="158.842102" />
            <Row value="11.79" />
            <Row value="-50.0" />
            <Row value="195.286697" />
            <Row value="-57.6572304" />
            <Row value="-50.0" />
            <Row value="322.65979" />
            <Row value="-90.0463028" />
            <Row value="-50.0" />
            <Row value="419.401306" />
            <Row value="-40.7104797" />
            <Row value="-50.0" />
            <Row value="419.107513" />
            <Row value="89.5146027" />
            <Row value="-50.0" />
            <Row value="265.276398" />
            <Row value="55.0293083" />
            <Row value="-50.0" />
            <Row value="195.787704" />
            <Row value="27.2889595" />
            <Row value="-50.0" />
            <Row value="49.9999809" />
        </Column>
        <Column name="BankObjectNameHash" type="uint32">
            <Row value="0x9f329e28" />
        </Column>
        <Column name="ProgId" type="uint32">
            <Row value="0x4dba9bb1" />
        </Column>
    </Object>
    <Object version="0" name="0x63b686f5" parent_object_file="Field_Common.kidsobjdb" parent_object="FE4SoundPlaceableEmitterPrism［Basic］">
        <Column name="WorldScale" type="float">
            <Row value="60.0" />
            <Row value="40.0" />
            <Row value="20.0" />
        </Column>
        <Column name="WorldPosition" type="float">
            <Row value="52000.0" />
            <Row value="28000.0" />
            <Row value="51000.0" />
        </Column>
        <Column name="WorldQuaternion" type="float">
            <Row value="0.00788756087" />
            <Row value="0.25414741" />
            <Row value="0.0104539599" />
            <Row value="0.967076778" />
        </Column>
        <Column name="Height" type="float">
            <Row value="99.9998322" />
        </Column>
        <Column name="PositionArray" type="float">
            <Row value="50.0" />
            <Row value="-50.0" />
            <Row value="50.0" />
            <Row value="50.0" />
            <Row value="-50.0" />
            <Row value="-50.0" />
            <Row value="-116.363998" />
            <Row value="-50.0" />
            <Row value="-62.5708084" />
            <Row value="-74.938942" />
            <Row value="-50.0" />
            <Row value="182.464401" />
            <Row value="-24.7413101" />
            <Row value="-50.0" />
            <Row value="50.0000687" />
        </Column>
        <Column name="BankObjectNameHash" type="uint32">
            <Row value="0x9f329e28" />
        </Column>
        <Column name="ProgId" type="uint32">
            <Row value="0x4dba9bb1" />
        </Column>
    </Object>
    <Object version="0" name="0x98d6cf0a" parent_object_file="Field_Common.kidsobjdb" parent_object="FE4SoundPlaceableEmitterLine［Basic］">
        <Column name="WorldScale" type="float">
            <Row value="1.0" />
            <Row value="1.0" />
            <Row value="1.0" />
        </Column>
        <Column name="WorldPosition" type="float">
            <Row value="46143.8086" />
            <Row value="31092.4238" />
            <Row value="38135.793" />
        </Column>
        <Column name="WorldQuaternion" type="float">
            <Row value="-0.724179327" />
            <Row value="-0.0612644702" />
            <Row value="0.0648808479" />
            <Row value="0.68381393" />
        </Column>
        <Column name="PositionArray" type="float">
            <Row value="100.949203" />
            <Row value="57.8183594" />
            <Row value="842.324219" />
            <Row value="-236.289093" />
            <Row value="270.332001" />
            <Row value="-1144.05896" />
        </Column>
        <Column name="SegmentIndexArray" type="uint32">
            <Row value="0x00000000" />
            <Row value="0x00000001" />
        </Column>
        <Column name="BankObjectNameHash" type="uint32">
            <Row value="0x9f329e28" />
        </Column>
        <Column name="ProgId" type="uint32">
            <Row value="0x52223abd" />
        </Column>
    </Object>
    <Object version="0" name="0xd1b72fa9" parent_object_file="Field_Common.kidsobjdb" parent_object="FE4SoundPlaceableEmitterLine［Basic］">
        <Column name="WorldScale" type="float">
            <Row value="1.0" />
            <Row value="1.0" />
            <Row value="1.0" />
        </Column>
        <Column name="WorldPosition" type="float">
            <Row value="41641.6992" />
            <Row value="30792.8965" />
            <Row value="38500.4336" />
        </Column>
        <Column name="WorldQuaternion" type="float">
            <Row value="-0.772462249" />
            <Row value="-0.0300299469" />
            <Row value="0.0366292559" />
            <Row value="0.633291543" />
        </Column>
        <Column name="PositionArray" type="float">
            <Row value="100.949203" />
            <Row value="57.8183594" />
            <Row value="842.324219" />
            <Row value="-236.289093" />
            <Row value="270.332001" />
            <Row value="-1144.05896" />
        </Column>
        <Column name="SegmentIndexArray" type="uint32">
            <Row value="0x00000000" />
            <Row value="0x00000001" />
        </Column>
        <Column name="BankObjectNameHash" type="uint32">
            <Row value="0x9f329e28" />
        </Column>
        <Column name="ProgId" type="uint32">
            <Row value="0x52223abd" />
        </Column>
    </Object>
    <Object version="0" name="0xd2c8ce5b" parent_object_file="Field_Common.kidsobjdb" parent_object="FE4SoundPlaceableEmitterPrism［Basic］">
        <Column name="WorldScale" type="float">
            <Row value="20.0" />
            <Row value="39.8719368" />
            <Row value="1.50361502" />
        </Column>
        <Column name="WorldPosition" type="float">
            <Row value="44924.6992" />
            <Row value="25607.6426" />
            <Row value="59775.168" />
        </Column>
        <Column name="WorldQuaternion" type="float">
            <Row value="-0.506866097" />
            <Row value="-0.52204442" />
            <Row value="-0.508217692" />
            <Row value="0.460728586" />
        </Column>
        <Column name="BankObjectNameHash" type="uint32">
            <Row value="0x9f329e28" />
        </Column>
        <Column name="ProgId" type="uint32">
            <Row value="0x4dba9bb1" />
        </Column>
    </Object>
    <Object version="0" name="0xe3c2b5ad" parent_object_file="Field_Common.kidsobjdb" parent_object="FE4SoundPlaceableEmitterBox［Basic］">
        <Column name="WorldScale" type="float">
            <Row value="284.046997" />
            <Row value="1200.00024" />
            <Row value="63.5078087" />
        </Column>
        <Column name="WorldPosition" type="float">
            <Row value="74994.4453" />
            <Row value="37377.0938" />
            <Row value="75603.0859" />
        </Column>
        <Column name="WorldQuaternion" type="float">
            <Row value="0.0" />
            <Row value="0.0" />
            <Row value="0.00978948176" />
            <Row value="0.999952078" />
        </Column>
        <Column name="BankObjectNameHash" type="uint32">
            <Row value="0x9f329e28" />
        </Column>
        <Column name="ProgId" type="uint32">
            <Row value="0x52223abd" />
        </Column>
        <Column name="Level" type="float">
            <Row value="0.806666672" />
        </Column>
    </Object>
    <Object version="0" name="0xe63f0b13" type="TypeInfo::Object::Sound::ReverbSetting">
        <Column name="DefaultPresetNameHash" type="uint32">
            <Row value="0x4a050832" />
        </Column>
        <Column name="DefaultVolume" type="float">
            <Row value="1.0" />
        </Column>
        <Column name="DefaultFadeTime" type="int32">
            <Row value="0" />
        </Column>
    </Object>
    <Object version="0" name="0xf06553f9" parent_object_file="Field_Common.kidsobjdb" parent_object="FE4SoundPlaceableEmitterPrism［Basic］">
        <Column name="WorldScale" type="float">
            <Row value="150.0" />
            <Row value="150.0" />
            <Row value="150.0" />
        </Column>
        <Column name="WorldPosition" type="float">
            <Row value="32009.5" />
            <Row value="13000.0" />
            <Row value="95829.7891" />
        </Column>
        <Column name="WorldQuaternion" type="float">
            <Row value="0.0069078994" />
            <Row value="0.0987338349" />
            <Row value="0.00951436162" />
            <Row value="0.99504441" />
        </Column>
        <Column name="Height" type="float">
            <Row value="99.9999771" />
        </Column>
        <Column name="PositionArray" type="float">
            <Row value="50.0" />
            <Row value="-50.0" />
            <Row value="50.0" />
            <Row value="50.0" />
            <Row value="-50.0" />
            <Row value="-50.0" />
            <Row value="50.0282707" />
            <Row value="-50.0" />
            <Row value="-248.009201" />
            <Row value="5.46736622" />
            <Row value="-50.0" />
            <Row value="-318.758087" />
            <Row value="-50.0" />
            <Row value="-50.0" />
            <Row value="-50.0" />
            <Row value="-50.0" />
            <Row value="-50.0" />
            <Row value="50.0" />
            <Row value="85.7808228" />
            <Row value="-50.0" />
            <Row value="229.524002" />
            <Row value="156.432297" />
            <Row value="-50.0" />
            <Row value="113.439102" />
            <Row value="179.911407" />
            <Row value="-50.0" />
            <Row value="80.673912" />
            <Row value="181.849792" />
            <Row value="-50.0" />
            <Row value="75.172493" />
            <Row value="140.595001" />
            <Row value="-50.0" />
            <Row value="88.6644516" />
        </Column>
        <Column name="BankObjectNameHash" type="uint32">
            <Row value="0x9f329e28" />
        </Column>
        <Column name="ProgId" type="uint32">
            <Row value="0x4dba9bb1" />
        </Column>
    </Object>
    <Object version="0" name="0xf271262c" parent_object_file="Field_Common.kidsobjdb" parent_object="FE4SoundPlaceableEmitterBox［Basic］">
        <Column name="WorldScale" type="float">
            <Row value="431.253906" />
            <Row value="1500.0" />
            <Row value="107.992188" />
        </Column>
        <Column name="WorldPosition" type="float">
            <Row value="67160.5156" />
            <Row value="36439.9102" />
            <Row value="78003.6563" />
        </Column>
        <Column name="WorldQuaternion" type="float">
            <Row value="0.0" />
            <Row value="0.0" />
            <Row value="0.0" />
            <Row value="1.0" />
        </Column>
        <Column name="BankObjectNameHash" type="uint32">
            <Row value="0x9f329e28" />
        </Column>
        <Column name="ProgId" type="uint32">
            <Row value="0x52223abd" />
        </Column>
        <Column name="Level" type="float">
            <Row value="0.74000001" />
        </Column>
    </Object>
</KidsObjDB>
